LICENSE
MANIFEST.in
README.md
requirements.txt
setup.cfg
setup.py
wis_processor/__init__.py
wis_processor/kriging.py
wis_processor/mean.py
wis_processor/voronoi.py
wis_processor/watershed.py
wis_processor/wis_processor.py
wis_processor.egg-info/PKG-INFO
wis_processor.egg-info/SOURCES.txt
wis_processor.egg-info/dependency_links.txt
wis_processor.egg-info/not-zip-safe
wis_processor.egg-info/requires.txt
wis_processor.egg-info/top_level.txt