Metadata-Version: 2.1
Name: wis-processor
Version: 0.0.1
Summary: gistools for WIS
Home-page: https://github.com/zjf014/wis-processor
Author: Jeff Zhu
Author-email: zjf014@gmail.com
License: MIT license
Keywords: wis_processor
Classifier: Development Status :: 2 - Pre-Alpha
Classifier: Intended Audience :: Developers
Classifier: License :: OSI Approved :: MIT License
Classifier: Natural Language :: English
Classifier: Programming Language :: Python :: 3
Classifier: Programming Language :: Python :: 3.7
Classifier: Programming Language :: Python :: 3.8
Classifier: Programming Language :: Python :: 3.9
Requires-Python: >=3.7
License-File: LICENSE
